stasher.py
stasher-1.0.1.dist-info/DESCRIPTION.rst
stasher-1.0.1.dist-info/METADATA
stasher-1.0.1.dist-info/RECORD
stasher-1.0.1.dist-info/WHEEL
stasher-1.0.1.dist-info/entry_points.txt
stasher-1.0.1.dist-info/metadata.json
stasher-1.0.1.dist-info/top_level.txt
