Metadata-Version: 2.0
Name: stasher
Version: 1.0.1
Summary: Utility for stashing files temporarily on remote server.
Home-page: https://github.com/andreif/stasher
Author: Andrei Fokau
Author-email: andrei@5monkeys.se
License: MIT
Download-URL: https://github.com/andreif/stasher/tarball/1.0.1
Keywords: stash,travis,coverage
Platform: UNKNOWN
Classifier: Environment :: Web Environment
Classifier: Natural Language :: English
Classifier: Intended Audience :: Developers
Classifier: License :: OSI Approved :: MIT License
Classifier: Operating System :: OS Independent
Classifier: Programming Language :: Python
Classifier: Programming Language :: Python :: 2
Classifier: Programming Language :: Python :: 2.7
Classifier: Programming Language :: Python :: 3
Classifier: Programming Language :: Python :: 3.4
Classifier: Programming Language :: Python :: 3.5
Classifier: Programming Language :: Python :: 3.6
Classifier: Topic :: Internet :: WWW/HTTP :: Dynamic Content
Classifier: Topic :: Software Development :: Libraries :: Python Modules
Requires-Dist: requests (==2.13.0)
